pydocks/__init__.py
pydocks/alpine.py
pydocks/opentofu.py
pydocks/plugin.py
pydocks/postgresql.py
pydocks/py.typed
pydocks/redis.py
pydocks/ubuntu.py
pydocks/valkey.py
pydocks/vault.py
pydocks/opentofu_resources/example.tf
pydocks/opentofu_resources/example.txt
pydocks/opentofu_resources/main.tf
pydocks/opentofu_resources/ready
pydocks/vault_resources/test-vault-init.sh
pydocks/vault_resources/vault-test.json
pydocks-1.10.0.dist-info/METADATA
pydocks-1.10.0.dist-info/WHEEL
pydocks-1.10.0.dist-info/entry_points.txt
pydocks-1.10.0.dist-info/licenses/LICENSE
pydocks-1.10.0.dist-info/RECORD
