Metadata-Version: 2.4
Name: pydocks
Version: 1.10.0
Summary: Pytest fixures for running tests with Docker containers
Project-URL: homepage, https://github.com/sylvainmouquet/pydocks
Project-URL: documentation, https://github.com/sylvainmouquet/pydocks
Project-URL: repository, https://github.com/sylvainmouquet/pydocks
Project-URL: changelog, https://github.com/sylvainmouquet/pydocks/releases
Author-email: Sylvain Mouquet <sylvain.mouquet@gmail.com>
License: MIT
License-File: LICENSE
Keywords: alpine,containers,docker,opentofu,postgresql,pydocks,redis,test,ubuntu,valkey,vault
Classifier: Development Status :: 5 - Production/Stable
Classifier: Framework :: Pytest
Classifier: Intended Audience :: Developers
Classifier: License :: OSI Approved :: MIT License
Classifier: Programming Language :: Python
Classifier: Programming Language :: Python :: 3
Classifier: Programming Language :: Python :: 3.10
Classifier: Programming Language :: Python :: 3.11
Classifier: Programming Language :: Python :: 3.12
Classifier: Programming Language :: Python :: 3.13
Classifier: Topic :: Software Development :: Libraries :: Python Modules
Requires-Python: >=3.10
